pinta/api/__init__.py
pinta/api/__main__.py
pinta_api-0.0.1.dist-info/entry_points.txt
pinta_api-0.0.1.dist-info/LICENSE
pinta_api-0.0.1.dist-info/WHEEL
pinta_api-0.0.1.dist-info/METADATA
pinta_api-0.0.1.dist-info/RECORD
